sort_all.py
sort_all-1.3.0.dist-info/LICENSE
sort_all-1.3.0.dist-info/METADATA
sort_all-1.3.0.dist-info/WHEEL
sort_all-1.3.0.dist-info/entry_points.txt
sort_all-1.3.0.dist-info/top_level.txt
sort_all-1.3.0.dist-info/RECORD
