Metadata-Version: 2.1
Name: sort_all
Version: 1.3.0
Summary: Automatically Sort __all__ records alphabetically
Home-page: https://github.com/aio-libs/sort-all
Author: Andrew Svetlov
Author-email: andrew.svetlov@gmail.com
License: Apache-2.0
Classifier: License :: OSI Approved :: Apache Software License
Classifier: Programming Language :: Python :: 3
Classifier: Programming Language :: Python :: 3 :: Only
Requires-Python: >=3.9
License-File: LICENSE
Requires-Dist: tokenize-rt >=3.0.1
